vaantamil/__init__.py
vaantamil/__main__.py
vaantamil/meimmayakkam.py
vaantamil/utility.py
vaantamil-0.1.2.dist-info/licenses/LICENSE
vaantamil-0.1.2.dist-info/METADATA
vaantamil-0.1.2.dist-info/WHEEL
vaantamil-0.1.2.dist-info/top_level.txt
vaantamil-0.1.2.dist-info/RECORD
