Metadata-Version: 2.4
Name: vaantamil
Version: 0.1.2
Summary: Tamil Morphological Analyzer and Grammar Engine
Author-email: Priya Saravanan <writemailtovaantamil@gmail.com>
Project-URL: Homepage, https://vaantamil.com
Project-URL: Source, https://github.com/vaantamil/vaantamil
Classifier: Programming Language :: Python :: 3
Classifier: License :: OSI Approved :: MIT License
Classifier: Operating System :: OS Independent
Requires-Python: >=3.10
License-File: LICENSE
Dynamic: license-file
